vtoo/__init__.py
vtoo/vision_process.py
vtoo-0.0.1.dist-info/LICENSE
vtoo-0.0.1.dist-info/WHEEL
vtoo-0.0.1.dist-info/METADATA
vtoo-0.0.1.dist-info/RECORD
