Metadata-Version: 2.1
Name: vtoo
Version: 0.0.1
Summary: visual tool
Author-email: calcuis <info@calcu.io>
Classifier: License :: OSI Approved :: Apache Software License
Requires-Dist: decord
Requires-Dist: torchcodec
Project-URL: Repository, https://github.com/calcuis/vtoo
